Workbook

Sheet README
A1: OG-OIP Excel workbook
A3: All operational, production, financial, maintenance, inventory, sensor and HSE data in this project are synthetic/simulated and created for portfolio demonstration purposes. They do not represent actual operations of a real company.
A5: Sheets: Assumptions (inputs, blue), Field_Monthly (synthetic data from mart_field_monthly), Field_Summary (SUMIFS formulas),
A6: Equipment (synthetic; availability/MTBF/MTTR are formulas), Executive_KPIs (formulas), Volve_Real and BSEE_Real (REAL user-supplied data, separate from PetroNexa).
A7: Real-data sheets are not linked to the synthetic sheets. Blue font = editable assumption; black = formula or data.
A8: Regenerate with scripts/build_excel.py after re-running the pipeline.

Sheet Executive_KPIs
A1: Executive KPIs - SYNTHETIC PetroNexa Energy data (formulas)
A3: Total oil produced (bbl) | B3: =Field_Summary!B6 -> 13352299
A4: Production loss vs simulated potential (%) | B4: =Field_Summary!E6 -> 0.093925674
A5: Revenue (USD, synthetic) | B5: =Field_Summary!F6 -> 9.56149e+08
A6: Operating cost (USD, synthetic) | B6: =Field_Summary!G6 -> 3.1423661e+08
A7: Operating margin (USD, synthetic) | B7: =Field_Summary!J6 -> 6.4191238e+08
A8: Estimated lost revenue (USD) | B8: =Field_Summary!K6 -> 95544790
A9: Failures (corrective events) | B9: =SUM(Equipment!F2:F49) -> 412
A10: Fleet MTBF (hours) | B10: =(SUM(Equipment!I2:I49)-SUM(Equipment!G2:G49))/SUM(Equipment!F2:F49) -> 3029.8375
A11: Fleet MTTR (hours) | B11: =SUM(Equipment!H2:H49)/SUM(Equipment!F2:F49) -> 25.293374
A12: Fleet availability (%) | B12: =100*(SUM(Equipment!I2:I49)-SUM(Equipment!G2:G49))/SUM(Equipment!I2:I49) -> 98.867492
A13: Total maintenance cost (USD) | B13: =SUM(Equipment!J2:J49) -> 9680324

Sheet Assumptions
A1: Assumption | B1: Value | C1: Source / note
A2: Barrels per Sm3 (Volve conversion) | B2: 6.28981 | C2: Unit conversion constant used in the pipeline (config.py)
A3: Mcf per BOE | B3: 6 | C3: Industry convention 6 mcf = 1 BOE
A4: Exposure hours per producing well-day | B4: 30 | C4: Synthetic assumption for HSE rates
A5: Incident-rate base hours | B5: 200000 | C5: Per 200,000 hours convention

Sheet Field_Monthly
A1: field_id | B1: month | C1: oil_bbl | D1: gas_mcf | E1: potential_bbl | F1: loss_bbl | G1: oil_sold_bbl | H1: gas_sold_mcf | I1: revenue_usd | J1: opex_total_usd | K1: cost_maintenance_usd | L1: lost_revenue_usd
A2: FIELD-001 | B2: 44562 | C2: 133148.9 | D2: 121539.4 | E2: 142729.8 | F2: 9580.9 | G2: 131107.7 | H2: 111988.1 | I2: 8985693.9 | J2: 2629898.4 | K2: 39147.51 | L2: 632277.68
A3: FIELD-001 | B3: 44593 | C3: 118887.18 | D3: 108681.6 | E3: 127976.4 | F3: 9089.2167 | G3: 117096.1 | H3: 99925.9 | I3: 7878743 | J3: 2393131 | K3: 70620.67 | L3: 581118.01
A4: FIELD-001 | B4: 44621 | C4: 120971.33 | D4: 111278.6 | E4: 139464.2 | F4: 18492.871 | G4: 119129.5 | H4: 102540.4 | I4: 8207585.4 | J4: 2579908.4 | K4: 93298.84 | L4: 1208181.3
A5: FIELD-001 | B5: 44652 | C5: 125147.24 | D5: 116911.8 | E5: 132618.9 | F5: 7471.663 | G5: 123410 | H5: 107446.8 | I5: 9566776.4 | J5: 2481889.4 | K5: 5647.73 | L5: 554511.34
A6: FIELD-001 | B6: 44682 | C6: 123640.69 | D6: 115549.8 | E6: 135013.6 | F6: 11372.908 | G6: 121805.2 | H6: 106299.7 | I6: 10047158 | J6: 2574696.6 | K6: 69121.76 | L6: 913898.3
A7: FIELD-001 | B7: 44713 | C7: 117344.61 | D7: 109830.3 | E7: 128373 | F7: 11028.391 | G7: 115941 | H7: 101319.8 | I7: 8796475 | J7: 2523904.7 | K7: 94981.87 | L7: 805325.43
A8: FIELD-001 | B8: 44743 | C8: 135711.83 | D8: 134234.9 | E8: 143836.1 | F8: 8124.2685 | G8: 133679.3 | H8: 123596.3 | I8: 11420739 | J8: 2674897.1 | K8: 12866.79 | L8: 665659.38
A9: FIELD-001 | B9: 44774 | C9: 135037.6 | D9: 134839.8 | E9: 144842.7 | F9: 9805.1 | G9: 133028.5 | H9: 124086 | I9: 10399913 | J9: 2682120.3 | K9: 32653.25 | L9: 731914.7
A10: FIELD-001 | B10: 44805 | C10: 127490.77 | D10: 127658.6 | E10: 136974.2 | F10: 9483.4256 | G10: 125668.4 | H10: 117579.4 | I10: 9283548.9 | J10: 2564043.6 | K10: 21606.91 | L10: 665375.68
A11: FIELD-001 | B11: 44835 | C11: 126319 | D11: 125535.2 | E11: 138481.6 | F11: 12162.596 | G11: 124577.7 | H11: 115631.2 | I11: 8875767.5 | J11: 2627642.2 | K11: 62116.07 | L11: 826302.39
A12: FIELD-001 | B12: 44866 | C12: 125627.41 | D12: 126642.6 | E12: 131621.6 | F12: 5994.1931 | G12: 123676.9 | H12: 116376.1 | I12: 9947797 | J12: 2524137.5 | K12: 13284.66 | L12: 460723.47
A13: FIELD-001 | B13: 44896 | C13: 121010.6 | D13: 122054 | E13: 134159.5 | F13: 13148.9 | G13: 119231.3 | H13: 112316.7 | I13: 9404273.4 | J13: 2659774 | K13: 93295.54 | L13: 988125.79
... A145: FIELD-004 | B145: 45627 | C145: 80588.879 | D145: 121111.4 | E145: 85597.7 | F145: 5008.8207 | G145: 79317.1 | H145: 111440.3 | I145: 5996065.3 | J145: 1978492.6 | K145: 46055.09 | L145: 351993.14

Sheet Field_Summary
A1: field_id | B1: oil_bbl | C1: potential_bbl | D1: loss_bbl | E1: loss_pct | F1: revenue_usd | G1: opex_usd | H1: cost_per_bbl_oil_sold | I1: cost_per_boe | J1: operating_margin_usd | K1: lost_revenue_usd
A2: FIELD-001 | B2: =SUMIFS(Field_Monthly!$C$2:$C$145,Field_Monthly!$A$2:$A$145,$A2) -> 4358664.6 | C2: =SUMIFS(Field_Monthly!$E$2:$E$145,Field_Monthly!$A$2:$A$145,$A2) -> 4776026.5 | D2: =SUMIFS(Field_Monthly!$F$2:$F$145,Field_Monthly!$A$2:$A$145,$A2) -> 417362.02 | E2: =D2/C2 -> 0.087386873 | F2: =SUMIFS(Field_Monthly!$I$2:$I$145,Field_Monthly!$A$2:$A$145,$A2) -> 3.1293564e+08 | G2: =SUMIFS(Field_Monthly!$J$2:$J$145,Field_Monthly!$A$2:$A$145,$A2) -> 95069746 | H2: =G2/SUMIFS(Field_Monthly!$G$2:$G$145,Field_Monthly!$A$2:$A$145,$A2) -> 22.136966 | I2: =G2/(SUMIFS(Field_Monthly!$G$2:$G$145,Field_Monthly!$A$2:$A$145,$A2)+SUMIFS(Field_Monthly!$H$2:$H$145,Field_Monthly!$A$2:$A$145,$A2)/Assumptions!$B$3) -> 18.977104 | J2: =F2-G2 -> 2.1786589e+08 | K2: =SUMIFS(Field_Monthly!$L$2:$L$145,Field_Monthly!$A$2:$A$145,$A2) -> 28821086
A3: FIELD-002 | B3: =SUMIFS(Field_Monthly!$C$2:$C$145,Field_Monthly!$A$2:$A$145,$A3) -> 3937987.8 | C3: =SUMIFS(Field_Monthly!$E$2:$E$145,Field_Monthly!$A$2:$A$145,$A3) -> 4385875.1 | D3: =SUMIFS(Field_Monthly!$F$2:$F$145,Field_Monthly!$A$2:$A$145,$A3) -> 447887.34 | E3: =D3/C3 -> 0.10212041 | F3: =SUMIFS(Field_Monthly!$I$2:$I$145,Field_Monthly!$A$2:$A$145,$A3) -> 2.8580352e+08 | G3: =SUMIFS(Field_Monthly!$J$2:$J$145,Field_Monthly!$A$2:$A$145,$A3) -> 87120079 | H3: =G3/SUMIFS(Field_Monthly!$G$2:$G$145,Field_Monthly!$A$2:$A$145,$A3) -> 22.463479 | I3: =G3/(SUMIFS(Field_Monthly!$G$2:$G$145,Field_Monthly!$A$2:$A$145,$A3)+SUMIFS(Field_Monthly!$H$2:$H$145,Field_Monthly!$A$2:$A$145,$A3)/Assumptions!$B$3) -> 19.424528 | J3: =F3-G3 -> 1.9868344e+08 | K3: =SUMIFS(Field_Monthly!$L$2:$L$145,Field_Monthly!$A$2:$A$145,$A3) -> 31570569
A4: FIELD-003 | B4: =SUMIFS(Field_Monthly!$C$2:$C$145,Field_Monthly!$A$2:$A$145,$A4) -> 2708874.3 | C4: =SUMIFS(Field_Monthly!$E$2:$E$145,Field_Monthly!$A$2:$A$145,$A4) -> 2991164.4 | D4: =SUMIFS(Field_Monthly!$F$2:$F$145,Field_Monthly!$A$2:$A$145,$A4) -> 282290.1 | E4: =D4/C4 -> 0.094374652 | F4: =SUMIFS(Field_Monthly!$I$2:$I$145,Field_Monthly!$A$2:$A$145,$A4) -> 1.8642239e+08 | G4: =SUMIFS(Field_Monthly!$J$2:$J$145,Field_Monthly!$A$2:$A$145,$A4) -> 68759914 | H4: =G4/SUMIFS(Field_Monthly!$G$2:$G$145,Field_Monthly!$A$2:$A$145,$A4) -> 25.73173 | I4: =G4/(SUMIFS(Field_Monthly!$G$2:$G$145,Field_Monthly!$A$2:$A$145,$A4)+SUMIFS(Field_Monthly!$H$2:$H$145,Field_Monthly!$A$2:$A$145,$A4)/Assumptions!$B$3) -> 21.815747 | J4: =F4-G4 -> 1.1766248e+08 | K4: =SUMIFS(Field_Monthly!$L$2:$L$145,Field_Monthly!$A$2:$A$145,$A4) -> 18655136
A5: FIELD-004 | B5: =SUMIFS(Field_Monthly!$C$2:$C$145,Field_Monthly!$A$2:$A$145,$A5) -> 2346772.3 | C5: =SUMIFS(Field_Monthly!$E$2:$E$145,Field_Monthly!$A$2:$A$145,$A5) -> 2583361.7 | D5: =SUMIFS(Field_Monthly!$F$2:$F$145,Field_Monthly!$A$2:$A$145,$A5) -> 236589.44 | E5: =D5/C5 -> 0.091582003 | F5: =SUMIFS(Field_Monthly!$I$2:$I$145,Field_Monthly!$A$2:$A$145,$A5) -> 1.7098745e+08 | G5: =SUMIFS(Field_Monthly!$J$2:$J$145,Field_Monthly!$A$2:$A$145,$A5) -> 63286875 | H5: =G5/SUMIFS(Field_Monthly!$G$2:$G$145,Field_Monthly!$A$2:$A$145,$A5) -> 27.346226 | I5: =G5/(SUMIFS(Field_Monthly!$G$2:$G$145,Field_Monthly!$A$2:$A$145,$A5)+SUMIFS(Field_Monthly!$H$2:$H$145,Field_Monthly!$A$2:$A$145,$A5)/Assumptions!$B$3) -> 22.297789 | J5: =F5-G5 -> 1.0770057e+08 | K5: =SUMIFS(Field_Monthly!$L$2:$L$145,Field_Monthly!$A$2:$A$145,$A5) -> 16497999
A6: TOTAL | B6: =SUM(B2:B5) -> 13352299 | C6: =SUM(C2:C5) -> 14736428 | D6: =SUM(D2:D5) -> 1384128.9 | E6: =D6/C6 -> 0.093925674 | F6: =SUM(F2:F5) -> 9.56149e+08 | G6: =SUM(G2:G5) -> 3.1423661e+08 | J6: =SUM(J2:J5) -> 6.4191238e+08 | K6: =SUM(K2:K5) -> 95544790

Sheet Equipment
A1: equipment_id | B1: equipment_name | C1: equipment_type | D1: field_id | E1: criticality | F1: failures | G1: total_downtime_hours | H1: corrective_downtime_hours | I1: period_hours | J1: maintenance_cost_usd | K1: availability_pct | L1: mtbf_hours | M1: mttr_hours
A2: EQ-0001 | B2: Pump 001-01 | C2: Pump | D2: FIELD-001 | E2: Medium | F2: 8 | G2: 239.27 | H2: 167.95 | I2: 26304 | J2: 125650.46 | K2: =100*(I2-G2)/I2 -> 99.090366 | L2: =IF(F2>0,(I2-G2)/F2,"") -> 3258.0912 | M2: =IF(F2>0,H2/F2,"") -> 20.99375
A3: EQ-0002 | B3: Pump 001-02 | C3: Pump | D3: FIELD-001 | E3: Medium | F3: 13 | G3: 264.78 | H3: 190.03 | I3: 26304 | J3: 202572.34 | K3: =100*(I3-G3)/I3 -> 98.993385 | L3: =IF(F3>0,(I3-G3)/F3,"") -> 2003.0169 | M3: =IF(F3>0,H3/F3,"") -> 14.617692
A4: EQ-0003 | B4: Pump 001-03 | C4: Pump | D4: FIELD-001 | E4: Medium | F4: 9 | G4: 280.81 | H4: 194.47 | I4: 26304 | J4: 153794.75 | K4: =100*(I4-G4)/I4 -> 98.932444 | L4: =IF(F4>0,(I4-G4)/F4,"") -> 2891.4656 | M4: =IF(F4>0,H4/F4,"") -> 21.607778
A5: EQ-0004 | B5: Pump 001-04 | C5: Pump | D5: FIELD-001 | E5: Medium | F5: 13 | G5: 384.34 | H5: 311.58 | I5: 26304 | J5: 221848.6 | K5: =100*(I5-G5)/I5 -> 98.538853 | L5: =IF(F5>0,(I5-G5)/F5,"") -> 1993.82 | M5: =IF(F5>0,H5/F5,"") -> 23.967692
A6: EQ-0005 | B6: Compressor 001-05 | C6: Compressor | D6: FIELD-001 | E6: High | F6: 11 | G6: 518.26 | H6: 396.31 | I6: 26304 | J6: 350545.17 | K6: =100*(I6-G6)/I6 -> 98.029729 | L6: =IF(F6>0,(I6-G6)/F6,"") -> 2344.1582 | M6: =IF(F6>0,H6/F6,"") -> 36.028182
A7: EQ-0006 | B7: Compressor 001-06 | C7: Compressor | D7: FIELD-001 | E7: High | F7: 10 | G7: 513.47 | H7: 389.25 | I7: 26304 | J7: 351927.69 | K7: =100*(I7-G7)/I7 -> 98.047939 | L7: =IF(F7>0,(I7-G7)/F7,"") -> 2579.053 | M7: =IF(F7>0,H7/F7,"") -> 38.925
A8: EQ-0007 | B8: Separator 001-07 | C8: Separator | D8: FIELD-001 | E8: High | F8: 5 | G8: 229.41 | H8: 149.35 | I8: 26304 | J8: 149266.79 | K8: =100*(I8-G8)/I8 -> 99.127851 | L8: =IF(F8>0,(I8-G8)/F8,"") -> 5214.918 | M8: =IF(F8>0,H8/F8,"") -> 29.87
A9: EQ-0008 | B9: Separator 001-08 | C9: Separator | D9: FIELD-001 | E9: Medium | F9: 7 | G9: 192.28 | H9: 125.48 | I9: 26304 | J9: 168077.42 | K9: =100*(I9-G9)/I9 -> 99.269009 | L9: =IF(F9>0,(I9-G9)/F9,"") -> 3730.2457 | M9: =IF(F9>0,H9/F9,"") -> 17.925714
A10: EQ-0009 | B10: Generator 001-09 | C10: Generator | D10: FIELD-001 | E10: High | F10: 7 | G10: 176.65 | H10: 104.28 | I10: 26304 | J10: 112435.06 | K10: =100*(I10-G10)/I10 -> 99.328429 | L10: =IF(F10>0,(I10-G10)/F10,"") -> 3732.4786 | M10: =IF(F10>0,H10/F10,"") -> 14.897143
A11: EQ-0010 | B11: Valve 001-10 | C11: Valve | D11: FIELD-001 | E11: Low | F11: 3 | G11: 103.68 | H11: 29.95 | I11: 26304 | J11: 131625.04 | K11: =100*(I11-G11)/I11 -> 99.605839 | L11: =IF(F11>0,(I11-G11)/F11,"") -> 8733.44 | M11: =IF(F11>0,H11/F11,"") -> 9.9833333
A12: EQ-0011 | B12: Heat Exchanger 001-11 | C12: Heat Exchanger | D12: FIELD-001 | E12: Medium | F12: 4 | G12: 282.87 | H12: 212.02 | I12: 26304 | J12: 102908.25 | K12: =100*(I12-G12)/I12 -> 98.924612 | L12: =IF(F12>0,(I12-G12)/F12,"") -> 6505.2825 | M12: =IF(F12>0,H12/F12,"") -> 53.005
A13: EQ-0012 | B13: Pipeline Equipment 001-12 | C13: Pipeline Equipment | D13: FIELD-001 | E13: Medium | F13: 2 | G13: 111.99 | H13: 48.01 | I13: 26304 | J13: 77905.56 | K13: =100*(I13-G13)/I13 -> 99.574247 | L13: =IF(F13>0,(I13-G13)/F13,"") -> 13096.005 | M13: =IF(F13>0,H13/F13,"") -> 24.005
... A49: EQ-0048 | B49: Pipeline Equipment 004-12 | C49: Pipeline Equipment | D49: FIELD-004 | E49: Medium | F49: 5 | G49: 185.39 | H49: 118.41 | I49: 26304 | J49: 116843.16 | K49: =100*(I49-G49)/I49 -> 99.295202 | L49: =IF(F49>0,(I49-G49)/F49,"") -> 5223.722 | M49: =IF(F49>0,H49/F49,"") -> 23.682

Sheet Volve_Real
A1: REAL data: Volve (user-supplied). Not PetroNexa. Yearly totals converted from Sm3.
A3: year | B3: oil_bbl | C3: gas_mcf | D3: water_bbl | E3: water_cut_pct
A4: 2008 | B4: 11097584 | C4: 9077240.6 | D4: 147866.77 | E4: =100*D4/(D4+B4) -> 1.3149029
A5: 2009 | B5: 16884316 | C5: 13277692 | D5: 1459888.4 | E5: =100*D5/(D5+B5) -> 7.9583088
A6: 2010 | B6: 10629166 | C6: 8614963.6 | D6: 11872613 | E6: =100*D6/(D6+B6) -> 52.762996
A7: 2011 | B7: 5333541.3 | C7: 4602218.6 | D7: 13778711 | E7: =100*D7/(D7+B7) -> 72.093602
A8: 2012 | B8: 3611648.7 | C8: 3185691.2 | D8: 13268993 | E8: =100*D8/(D8+B8) -> 78.604791
A9: 2013 | B9: 3509792.8 | C9: 3093136.1 | D9: 16204851 | E9: =100*D9/(D9+B9) -> 82.197027
A10: 2014 | B10: 4674004.9 | C10: 3947896.5 | D10: 17083570 | E10: =100*D10/(D10+B10) -> 78.517804
A11: 2015 | B11: 5420237.9 | C11: 4535249.5 | D11: 12641423 | E11: =100*D11/(D11+B11) -> 69.990368
A12: 2016 | B12: 1971038.1 | C12: 1768176.3 | D12: 9893030.9 | E12: =100*D12/(D12+B12) -> 83.386491

Sheet BSEE_Real
A1: REAL data: BSEE OGOR-A monthly totals (user-supplied; column meaning per author's understanding - verify with BSEE dictionary). Not PetroNexa.
A3: month | B3: oil_bbl | C3: gas_mcf | D3: water_bbl | E3: operators | F3: water_to_oil_ratio | G3: gas_to_oil_mcf_per_bbl
A4: 45658 | B4: 56034961 | C4: 58090056 | D4: 32822461 | E4: 47 | F4: =D4/B4 -> 0.58574969 | G4: =C4/B4 -> 1.0366752
A5: 45689 | B5: 49673730 | C5: 52394411 | D5: 30629985 | E5: 47 | F5: =D5/B5 -> 0.61662341 | G5: =C5/B5 -> 1.054771
A6: 45717 | B6: 56155887 | C6: 60550399 | D6: 34408007 | E6: 47 | F6: =D6/B6 -> 0.61272306 | G6: =C6/B6 -> 1.0782556
A7: 45748 | B7: 54903761 | C7: 58559171 | D7: 31204625 | E7: 46 | F7: =D7/B7 -> 0.56835132 | G7: =C7/B7 -> 1.0665785
A8: 45778 | B8: 57137177 | C8: 61281528 | D8: 32561877 | E8: 46 | F8: =D8/B8 -> 0.5698895 | G8: =C8/B8 -> 1.0725334
A9: 45809 | B9: 58469587 | C9: 62339306 | D9: 34784264 | E9: 46 | F9: =D9/B9 -> 0.59491209 | G9: =C9/B9 -> 1.0661835
A10: 45839 | B10: 59986591 | C10: 65722676 | D10: 33682184 | E10: 46 | F10: =D10/B10 -> 0.56149522 | G10: =C10/B10 -> 1.0956228
A11: 45870 | B11: 62996525 | C11: 67957109 | D11: 35333713 | E11: 44 | F11: =D11/B11 -> 0.56088352 | G11: =C11/B11 -> 1.0787438
A12: 45901 | B12: 61931894 | C12: 65699914 | D12: 35378355 | E12: 44 | F12: =D12/B12 -> 0.57124613 | G12: =C12/B12 -> 1.0608413
A13: 45931 | B13: 66501289 | C13: 70337281 | D13: 36845224 | E13: 43 | F13: =D13/B13 -> 0.55405278 | G13: =C13/B13 -> 1.057683
A14: 45962 | B14: 62095590 | C14: 65830080 | D14: 34001719 | E14: 43 | F14: =D14/B14 -> 0.54757059 | G14: =C14/B14 -> 1.060141
A15: 45992 | B15: 65078743 | C15: 69976474 | D15: 35983223 | E15: 43 | F15: =D15/B15 -> 0.55291822 | G15: =C15/B15 -> 1.0752585
... A21: 46174 | B21: 57419970 | C21: 59456793 | D21: 32601816 | E21: 40 | F21: =D21/B21 -> 0.56777835 | G21: =C21/B21 -> 1.0354724
